map_async.py
map_async-1.2.3.dist-info/METADATA
map_async-1.2.3.dist-info/WHEEL
map_async-1.2.3.dist-info/top_level.txt
map_async-1.2.3.dist-info/RECORD
