Metadata-Version: 2.1
Name: map-async
Version: 1.2.3
Summary: Multiprocess mapping with a integrated progress bar.
Home-page: https://github.com/kaniblu/map-async
Author: Kang Min Yoo
Author-email: kangmin.yoo@gmail.com
License: MIT
Keywords: asynchronous,map,multiprocessing
Platform: Operating System :: MacOS :: MacOS X
Platform: Operating System :: POSIX :: Linux
Classifier: Intended Audience :: Developers
Classifier: Topic :: Software Development :: Libraries :: Python Modules
Requires-Dist: tqdm (>=4.46.1)
